{
    "val": [
        {
            "drop": 0.3,
            "rec_drop": 0.3,
            "learning_rate": 0.8,
            "units": 15,
            "50": {
                "loss": 0.6399999856948853,
                "acc": 0.36000001430511475
            },
            "100": {
                "loss": 0.6399999856948853,
                "acc": 0.36000001430511475
            }
        },
        {
            "drop": 0.5,
            "rec_drop": 0.5,
            "learning_rate": 0.8,
            "units": 15,
            "50": {
                "loss": 0.36000001430511475,
                "acc": 0.6399999856948853
            },
            "100": {
                "loss": 0.36000001430511475,
                "acc": 0.6399999856948853
            }
        },
        {
            "drop": 0.7,
            "rec_drop": 0.7,
            "learning_rate": 0.8,
            "units": 15,
            "50": {
                "loss": 0.36000001430511475,
                "acc": 0.6399999856948853
            },
            "100": {
                "loss": 0.3871692419052124,
                "acc": 0.6100000143051147
            }
        }
    ]
}